[
    {
        "team-home": "Arsenal",
        "team-away": "Watford",
        "score-home": "0",
        "score-away": "0",
        "status": "",
        "start-time": "16:00"
    },
    {
        "team-home": "Burnley",
        "team-away": "Brighton & Hove Albion",
        "score-home": "0",
        "score-away": "0",
        "status": "",
        "start-time": "16:00"
    },
    {
        "team-home": "Chelsea",
        "team-away": "Wolverhampton Wanderers",
        "score-home": "0",
        "score-away": "0",
        "status": "",
        "start-time": "16:00"
    },
    {
        "team-home": "Crystal Palace",
        "team-away": "Tottenham Hotspur",
        "score-home": "0",
        "score-away": "0",
        "status": "",
        "start-time": "16:00"
    },
    {
        "team-home": "Everton",
        "team-away": "AFC Bournemouth",
        "score-home": "0",
        "score-away": "0",
        "status": "",
        "start-time": "16:00"
    },
    {
        "team-home": "Leicester City",
        "team-away": "Manchester United",
        "score-home": "0",
        "score-away": "0",
        "status": "",
        "start-time": "16:00"
    },
    {
        "team-home": "Manchester City",
        "team-away": "Norwich City",
        "score-home": "0",
        "score-away": "0",
        "status": "",
        "start-time": "16:00"
    },
    {
        "team-home": "Newcastle United",
        "team-away": "Liverpool",
        "score-home": "0",
        "score-away": "0",
        "status": "",
        "start-time": "16:00"
    },
    {
        "team-home": "Southampton",
        "team-away": "Sheffield United",
        "score-home": "0",
        "score-away": "0",
        "status": "",
        "start-time": "16:00"
    },
    {
        "team-home": "West Ham United",
        "team-away": "Aston Villa",
        "score-home": "0",
        "score-away": "0",
        "status": "",
        "start-time": "16:00"
    }
]